{
  "id": "ingenius-technologies",
  "title": "Ingenius Technologies",
  "subtitle": "Our powerful Partner Management Platform is designed to help companies track, manage, analyse and payout their market...",
  "tags": [
    "marketing-automation-&-campaign/lead-management"
  ],
  "category": "Other",
  "specType": "auto-detect",
  "authType": "api-key",
  "logo": "https://res.cloudinary.com/apideck/image/upload/v1554720484/catalog/ingenius-technologies/icon128x128.jpg",
  "website": "https://ingenioustechnologies.com"
}
